<?xml version="1.0" encoding="utf-8" ?><dwsync><file name="FLVPlayer_Progressive.swf" server="newhttpd.vjf.cnrs.fr//var/www/html/lacito/" local="3317383780" remote="110728703579" /><file name="Clear_Skin_1.swf" server="newhttpd.vjf.cnrs.fr//var/www/html/lacito/" local="3310995569" remote="72073997914" /><file name="Clear_Skin_2.swf" server="newhttpd.vjf.cnrs.fr//var/www/html/lacito/" local="3317383780" remote="72073997915" /><file name="Clear_Skin_3.swf" server="newhttpd.vjf.cnrs.fr//var/www/html/lacito/" local="3310995442" remote="72073997915" /><file name="sm.htm" server="newhttpd.vjf.cnrs.fr//var/www/html/lacito/" local="3354520108" remote="29124324955" /><file name="af.htm" server="newhttpd.vjf.cnrs.fr//var/www/html/lacito/" local="3354520108" remote="29124324954" /><file name="ea.htm" server="newhttpd.vjf.cnrs.fr//var/www/html/lacito/" local="3354520108" remote="29124324955" /><file name="fj.htm" server="newhttpd.vjf.cnrs.fr//var/www/html/lacito/" local="3354520108" remote="29124324955" /><file name="kv.htm" server="newhttpd.vjf.cnrs.fr//var/www/html/lacito/" local="3354520108" remote="29124324955" /><file name="ym.htm" server="newhttpd.vjf.cnrs.fr//var/www/html/lacito/" local="3354520108" remote="29124324955" /></dwsync>