<?xml version="1.0" encoding="utf-8" ?>
<dwsync>
<file name="conte_caledonie.htm" server="newhttpd.vjf.cnrs.fr//var/www/html/lacito/" local="129161500940000000" remote="129161500940000000" />
<file name="decouverte.htm" server="newhttpd.vjf.cnrs.fr//var/www/html/lacito/" local="129161500940000000" remote="129161500940000000" />
<file name="dzongkha.htm" server="newhttpd.vjf.cnrs.fr//var/www/html/lacito/" local="129161500940000000" remote="129161500940000000" />
<file name="enc_pygmee_aka.htm" server="newhttpd.vjf.cnrs.fr//var/www/html/lacito/" local="129161500950000000" remote="129161500950000000" />
<file name="etapes_creation.htm" server="newhttpd.vjf.cnrs.fr//var/www/html/lacito/" local="129161500950000000" remote="129161500950000000" />
<file name="japonais_3_syst.htm" server="newhttpd.vjf.cnrs.fr//var/www/html/lacito/" local="129161500970000000" remote="129161500970000000" />
<file name="langues_classes.htm" server="newhttpd.vjf.cnrs.fr//var/www/html/lacito/" local="129161500970000000" remote="129161500970000000" />
<file name="maya_nombres.htm" server="newhttpd.vjf.cnrs.fr//var/www/html/lacito/" local="129161500970000000" remote="129161500970000000" />
<file name="mofu_musique.htm" server="newhttpd.vjf.cnrs.fr//var/www/html/lacito/" local="129161500980000000" remote="129161500980000000" />
<file name="musique_societe.htm" server="newhttpd.vjf.cnrs.fr//var/www/html/lacito/" local="129161500980000000" remote="129161500980000000" />
<file name="numeration_gestuelle.htm" server="newhttpd.vjf.cnrs.fr//var/www/html/lacito/" local="129161500980000000" remote="129161500980000000" />
<file name="numerations_parlees.htm" server="newhttpd.vjf.cnrs.fr//var/www/html/lacito/" local="129161500980000000" remote="129161500980000000" />
<file name="qu_est_qu_un_nombre.htm" server="newhttpd.vjf.cnrs.fr//var/www/html/lacito/" local="129161500980000000" remote="129161500980000000" />
<file name="systeme_de_numeration.htm" server="newhttpd.vjf.cnrs.fr//var/www/html/lacito/" local="129161500980000000" remote="129161500980000000" />
<file name="tagalog.htm" server="newhttpd.vjf.cnrs.fr//var/www/html/lacito/" local="129161500980000000" remote="129161500980000000" />
<file name="wayana_musique.htm" server="newhttpd.vjf.cnrs.fr//var/www/html/lacito/" local="129161500980000000" remote="129161500980000000" />
<file name="xaracuu.html" server="newhttpd.vjf.cnrs.fr//var/www/html/lacito/" local="129161500980000000" remote="129161500980000000" />
</dwsync>