<?xml version="1.0" encoding="utf-8" ?>
<dwsync>
<file name="bril_ozanne-copie.gif" server="newhttpd.vjf.cnrs.fr//var/www/html/lacito/" local="128256426240000000" remote="128256426240000000" />
<file name="bril_ozanne-petit.gif" server="newhttpd.vjf.cnrs.fr//var/www/html/lacito/" local="129140699950000000" remote="129140699950000000" />
<file name="couveabzakh.gif" server="newhttpd.vjf.cnrs.fr//var/www/html/lacito/" local="129140699940000000" remote="129140699940000000" />
<file name="couveabzakhbig.gif" server="newhttpd.vjf.cnrs.fr//var/www/html/lacito/" local="128256426290000000" remote="128256426290000000" />
<file name="guide2006.gif" server="newhttpd.vjf.cnrs.fr//var/www/html/lacito/" local="128256426340000000" remote="128256426340000000" />
<file name="guide2006_sm.gif" server="newhttpd.vjf.cnrs.fr//var/www/html/lacito/" local="129140699940000000" remote="129140699940000000" />
<file name="JacquessonDeuri.gif" server="newhttpd.vjf.cnrs.fr//var/www/html/lacito/" local="128256426390000000" remote="128256426390000000" />
<file name="JacquessonDeuri_sm.gif" server="newhttpd.vjf.cnrs.fr//var/www/html/lacito/" local="129140699940000000" remote="129140699940000000" />
<file name="jso001-petit.gif" server="newhttpd.vjf.cnrs.fr//var/www/html/lacito/" local="129140699950000000" remote="129140699950000000" />
<file name="jso001.gif" server="newhttpd.vjf.cnrs.fr//var/www/html/lacito/" local="128256426400000000" remote="128256426400000000" />
<file name="lingtypo_sm.gif" server="newhttpd.vjf.cnrs.fr//var/www/html/lacito/" local="129140699940000000" remote="129140699940000000" />
<file name="LivreLangi.gif" server="newhttpd.vjf.cnrs.fr//var/www/html/lacito/" local="128256426440000000" remote="128256426440000000" />
<file name="LivreLangi_sm.gif" server="newhttpd.vjf.cnrs.fr//var/www/html/lacito/" local="129140699940000000" remote="129140699940000000" />
<file name="nashta.jpg" server="newhttpd.vjf.cnrs.fr//var/www/html/lacito/" local="128256426470000000" remote="128256426470000000" />
<file name="nashta_sm.gif" server="newhttpd.vjf.cnrs.fr//var/www/html/lacito/" local="129140699940000000" remote="129140699940000000" />
<file name="clo_plantes_med.jpg" server="newhttpd.vjf.cnrs.fr//var/www/html/lacito/" local="128256426250000000" remote="128256426250000000" />
<file name="CouvMolene250.jpg" server="newhttpd.vjf.cnrs.fr//var/www/html/lacito/" local="128256426310000000" remote="128256426310000000" />
<file name="CouvMolene65.jpg" server="newhttpd.vjf.cnrs.fr//var/www/html/lacito/" local="129140699880000000" remote="129140699880000000" />
<file name="leroy_mankon250.jpg" server="newhttpd.vjf.cnrs.fr//var/www/html/lacito/" local="128256426420000000" remote="128256426420000000" />
<file name="leroy_mankon65.jpg" server="newhttpd.vjf.cnrs.fr//var/www/html/lacito/" local="129140699930000000" remote="129140699930000000" />
<file name="Rivierre_bwatoo250.jpg" server="newhttpd.vjf.cnrs.fr//var/www/html/lacito/" local="128256426490000000" remote="128256426490000000" />
<file name="Rivierre_bwatoo65.jpg" server="newhttpd.vjf.cnrs.fr//var/www/html/lacito/" local="129140699940000000" remote="129140699940000000" />
<file name="fdl28.jpg" server="newhttpd.vjf.cnrs.fr//var/www/html/lacito/" local="128256426330000000" remote="128256426330000000" />
<file name="fdl28_sm.jpg" server="newhttpd.vjf.cnrs.fr//var/www/html/lacito/" local="129140699910000000" remote="129140699910000000" />
<file name="LivreLangi.jpg" server="newhttpd.vjf.cnrs.fr//var/www/html/lacito/" local="128256426440000000" remote="128256426440000000" />
<file name="BIG63_250.jpg" server="newhttpd.vjf.cnrs.fr//var/www/html/lacito/" local="128256426210000000" remote="128256426210000000" />
<file name="BIG63_65.jpg" server="newhttpd.vjf.cnrs.fr//var/www/html/lacito/" local="129140699900000000" remote="129140699900000000" />
<file name="Tournadre250.jpg" server="newhttpd.vjf.cnrs.fr//var/www/html/lacito/" local="128256426530000000" remote="128256426530000000" />
<file name="Tournadre65.jpg" server="newhttpd.vjf.cnrs.fr//var/www/html/lacito/" local="129140699940000000" remote="129140699940000000" />
<file name="coyaud_osmanthes250.jpg" server="newhttpd.vjf.cnrs.fr//var/www/html/lacito/" local="128256426320000000" remote="128256426320000000" />
<file name="coyaud_osmanthes65.jpg" server="newhttpd.vjf.cnrs.fr//var/www/html/lacito/" local="129140699900000000" remote="129140699900000000" />
<file name="hommages_250.jpg" server="newhttpd.vjf.cnrs.fr//var/www/html/lacito/" local="128256426360000000" remote="128256426360000000" />
<file name="hommages_65.jpg" server="newhttpd.vjf.cnrs.fr//var/www/html/lacito/" local="129140699950000000" remote="129140699950000000" />
<file name="hommages_137.jpg" server="newhttpd.vjf.cnrs.fr//var/www/html/lacito/" local="129364482610000000" remote="129364482610000000" />
<file name="Aka_II_8_65.jpg" server="newhttpd.vjf.cnrs.fr//var/www/html/lacito/" local="129140699890000000" remote="129140699890000000" />
<file name="aka_II_8_250.jpg" server="newhttpd.vjf.cnrs.fr//var/www/html/lacito/" local="128256426190000000" remote="128256426190000000" />
<file name="adoption250.jpg" server="newhttpd.vjf.cnrs.fr//var/www/html/lacito/" local="128257871390000000" remote="128257871390000000" />
<file name="adoption65.jpg" server="newhttpd.vjf.cnrs.fr//var/www/html/lacito/" local="129140699950000000" remote="129140699950000000" />
<file name="Aka_II_7_250.jpg" server="newhttpd.vjf.cnrs.fr//var/www/html/lacito/" local="129488961300000000" remote="129488961300000000" />
<file name="Aka_II_7_65.jpg" server="newhttpd.vjf.cnrs.fr//var/www/html/lacito/" local="129140699940000000" remote="129140699940000000" />
<file name="araki250.jpg" server="newhttpd.vjf.cnrs.fr//var/www/html/lacito/" local="128256426200000000" remote="128256426200000000" />
<file name="araki65.jpg" server="newhttpd.vjf.cnrs.fr//var/www/html/lacito/" local="129140699960000000" remote="129140699960000000" />
<file name="bafia250.jpg" server="newhttpd.vjf.cnrs.fr//var/www/html/lacito/" local="128256426200000000" remote="128256426200000000" />
<file name="bafia65.jpg" server="newhttpd.vjf.cnrs.fr//var/www/html/lacito/" local="129140699970000000" remote="129140699970000000" />
<file name="bril_ozanne.jpg" server="newhttpd.vjf.cnrs.fr//var/www/html/lacito/" local="128256426240000000" remote="128256426240000000" />
<file name="clo_plantes65.jpg" server="newhttpd.vjf.cnrs.fr//var/www/html/lacito/" local="129140699950000000" remote="129140699950000000" />
<file name="couvattente_65.jpg" server="newhttpd.vjf.cnrs.fr//var/www/html/lacito/" local="128256426270000000" remote="128256426270000000" />
<file name="insectes250.jpg" server="newhttpd.vjf.cnrs.fr//var/www/html/lacito/" local="128256426370000000" remote="128256426370000000" />
<file name="insectes65.jpg" server="newhttpd.vjf.cnrs.fr//var/www/html/lacito/" local="129140699950000000" remote="129140699950000000" />
<file name="interlocution250.jpg" server="newhttpd.vjf.cnrs.fr//var/www/html/lacito/" local="128256426380000000" remote="128256426380000000" />
<file name="interlocution65.jpg" server="newhttpd.vjf.cnrs.fr//var/www/html/lacito/" local="129140699970000000" remote="129140699970000000" />
<file name="lexmotiv250.jpg" server="newhttpd.vjf.cnrs.fr//var/www/html/lacito/" local="128256426420000000" remote="128256426420000000" />
<file name="lexmotiv65.jpg" server="newhttpd.vjf.cnrs.fr//var/www/html/lacito/" local="129140699960000000" remote="129140699960000000" />
<file name="limbudico250.jpg" server="newhttpd.vjf.cnrs.fr//var/www/html/lacito/" local="128256426430000000" remote="128256426430000000" />
<file name="limbudico65.jpg" server="newhttpd.vjf.cnrs.fr//var/www/html/lacito/" local="129140699960000000" remote="129140699960000000" />
<file name="pacificpidgin250.jpg" server="newhttpd.vjf.cnrs.fr//var/www/html/lacito/" local="128257917910000000" remote="128257917910000000" />
<file name="pacificpidgin65.jpg" server="newhttpd.vjf.cnrs.fr//var/www/html/lacito/" local="129140699950000000" remote="129140699950000000" />
<file name="payskanak250.jpg" server="newhttpd.vjf.cnrs.fr//var/www/html/lacito/" local="128256426480000000" remote="128256426480000000" />
<file name="payskanak65.jpg" server="newhttpd.vjf.cnrs.fr//var/www/html/lacito/" local="129140699970000000" remote="129140699970000000" />
<file name="scales250.jpg" server="newhttpd.vjf.cnrs.fr//var/www/html/lacito/" local="128257909440000000" remote="128257909440000000" />
<file name="scales65.jpg" server="newhttpd.vjf.cnrs.fr//var/www/html/lacito/" local="129140699950000000" remote="129140699950000000" />
<file name="semMwotlap250.jpg" server="newhttpd.vjf.cnrs.fr//var/www/html/lacito/" local="128256426520000000" remote="128256426520000000" />
<file name="semMwotlap65.jpg" server="newhttpd.vjf.cnrs.fr//var/www/html/lacito/" local="129140699950000000" remote="129140699950000000" />
<file name="yemen250.jpg" server="newhttpd.vjf.cnrs.fr//var/www/html/lacito/" local="128256877170000000" remote="128256877170000000" />
<file name="yemen65.jpg" server="newhttpd.vjf.cnrs.fr//var/www/html/lacito/" local="129140699960000000" remote="129140699960000000" />
<file name="aka_II_1_65.jpg" server="newhttpd.vjf.cnrs.fr//var/www/html/lacito/" local="129140699960000000" remote="129140699960000000" />
<file name="aka_II_5_65.jpg" server="newhttpd.vjf.cnrs.fr//var/www/html/lacito/" local="129140699950000000" remote="129140699950000000" />
<file name="aka_II_6_65.jpg" server="newhttpd.vjf.cnrs.fr//var/www/html/lacito/" local="129140699950000000" remote="129140699950000000" />
<file name="imagimer250.jpg" server="newhttpd.vjf.cnrs.fr//var/www/html/lacito/" local="128256426370000000" remote="128256426370000000" />
<file name="imagimer65.jpg" server="newhttpd.vjf.cnrs.fr//var/www/html/lacito/" local="129140699960000000" remote="129140699960000000" />
<file name="languagevariation65.jpg" server="newhttpd.vjf.cnrs.fr//var/www/html/lacito/" local="129140699960000000" remote="129140699960000000" />
<file name="tibetainmanuel250.jpg" server="newhttpd.vjf.cnrs.fr//var/www/html/lacito/" local="128256426530000000" remote="128256426530000000" />
<file name="tibetainmanuel65.jpg" server="newhttpd.vjf.cnrs.fr//var/www/html/lacito/" local="129140699950000000" remote="129140699950000000" />
<file name="langagevariation250.jpg" server="newhttpd.vjf.cnrs.fr//var/www/html/lacito/" local="128256426410000000" remote="128256426410000000" />
<file name="medisance65.jpg" server="newhttpd.vjf.cnrs.fr//var/www/html/lacito/" local="129401846890000000" remote="129401846890000000" />
<file name="contes_250.jpg" server="newhttpd.vjf.cnrs.fr//var/www/html/lacito/" local="128256909000000000" remote="128256909000000000" />
<file name="contes_65.jpg" server="newhttpd.vjf.cnrs.fr//var/www/html/lacito/" local="129140699940000000" remote="129140699940000000" />
<file name="rombi_thomas_250.jpg" server="newhttpd.vjf.cnrs.fr//var/www/html/lacito/" local="128256877430000000" remote="128256877430000000" />
<file name="rombi_thomas_65.jpg" server="newhttpd.vjf.cnrs.fr//var/www/html/lacito/" local="129140699930000000" remote="129140699930000000" />
<file name="DicoVdC_250.jpg" server="newhttpd.vjf.cnrs.fr//var/www/html/lacito/" local="128256912030000000" remote="128256912030000000" />
<file name="DicoVdC_65.jpg" server="newhttpd.vjf.cnrs.fr//var/www/html/lacito/" local="129140699940000000" remote="129140699940000000" />
<file name="tempsespace250.jpg" server="newhttpd.vjf.cnrs.fr//var/www/html/lacito/" local="128257883150000000" remote="128257883150000000" />
<file name="tempsespace65.jpg" server="newhttpd.vjf.cnrs.fr//var/www/html/lacito/" local="129140699940000000" remote="129140699940000000" />
<file name="coyaud_coraux65.jpg" server="newhttpd.vjf.cnrs.fr//var/www/html/lacito/" local="129140699950000000" remote="129140699950000000" />
<file name="coyaud_bucoliques250.jpg" server="newhttpd.vjf.cnrs.fr//var/www/html/lacito/" local="128272506460000000" remote="128272506460000000" />
<file name="coyaud_bucoliques65.jpg" server="newhttpd.vjf.cnrs.fr//var/www/html/lacito/" local="129140699940000000" remote="129140699940000000" />
<file name="AFA85-86_250.jpg" server="newhttpd.vjf.cnrs.fr//var/www/html/lacito/" local="128273480970000000" remote="128273480970000000" />
<file name="AFA85-86_65.jpg" server="newhttpd.vjf.cnrs.fr//var/www/html/lacito/" local="129140699960000000" remote="129140699960000000" />
<file name="bouquiaux_articles65.jpg" server="newhttpd.vjf.cnrs.fr//var/www/html/lacito/" local="129140699950000000" remote="129140699950000000" />
<file name="bouquiaux_articles_250.jpg" server="newhttpd.vjf.cnrs.fr//var/www/html/lacito/" local="128273481220000000" remote="128273481220000000" />
<file name="bouquiaux_birom1_250.jpg" server="newhttpd.vjf.cnrs.fr//var/www/html/lacito/" local="128273481270000000" remote="128273481270000000" />
<file name="bouquiaux_birom1_65.jpg" server="newhttpd.vjf.cnrs.fr//var/www/html/lacito/" local="129140699960000000" remote="129140699960000000" />
<file name="bouquiaux_birom2_250.jpg" server="newhttpd.vjf.cnrs.fr//var/www/html/lacito/" local="128273481320000000" remote="128273481320000000" />
<file name="bouquiaux_birom2_65.jpg" server="newhttpd.vjf.cnrs.fr//var/www/html/lacito/" local="128273481350000000" remote="128273481350000000" />
<file name="bouquiaux_birom3_250.jpg" server="newhttpd.vjf.cnrs.fr//var/www/html/lacito/" local="128273481390000000" remote="128273481390000000" />
<file name="bouquiaux_birom3_65.jpg" server="newhttpd.vjf.cnrs.fr//var/www/html/lacito/" local="128273481420000000" remote="128273481420000000" />
<file name="bril_diconelemwa250.jpg" server="newhttpd.vjf.cnrs.fr//var/www/html/lacito/" local="128273481450000000" remote="128273481450000000" />
<file name="bril_diconelemwa65.jpg" server="newhttpd.vjf.cnrs.fr//var/www/html/lacito/" local="129140699960000000" remote="129140699960000000" />
<file name="bril_lenelemwa250.jpg" server="newhttpd.vjf.cnrs.fr//var/www/html/lacito/" local="128273481510000000" remote="128273481510000000" />
<file name="bril_lenelemwa65.jpg" server="newhttpd.vjf.cnrs.fr//var/www/html/lacito/" local="129140699960000000" remote="129140699960000000" />
<file name="clo48_250.jpg" server="newhttpd.vjf.cnrs.fr//var/www/html/lacito/" local="128273481600000000" remote="128273481600000000" />
<file name="clo48_65.jpg" server="newhttpd.vjf.cnrs.fr//var/www/html/lacito/" local="129140699970000000" remote="129140699970000000" />
<file name="colombel_phonologie250.jpg" server="newhttpd.vjf.cnrs.fr//var/www/html/lacito/" local="128275127990000000" remote="128275127990000000" />
<file name="colombel_phonologie65.jpg" server="newhttpd.vjf.cnrs.fr//var/www/html/lacito/" local="129140699970000000" remote="129140699970000000" />
<file name="coyaud_banquise250.jpg" server="newhttpd.vjf.cnrs.fr//var/www/html/lacito/" local="128273481780000000" remote="128273481780000000" />
<file name="coyaud_banquise65.jpg" server="newhttpd.vjf.cnrs.fr//var/www/html/lacito/" local="129140699940000000" remote="129140699940000000" />
<file name="jaf72-2_250.jpg" server="newhttpd.vjf.cnrs.fr//var/www/html/lacito/" local="128273482000000000" remote="128273482000000000" />
<file name="jaf72-2_65.jpg" server="newhttpd.vjf.cnrs.fr//var/www/html/lacito/" local="129140699960000000" remote="129140699960000000" />
<file name="leblic_kanak250.jpg" server="newhttpd.vjf.cnrs.fr//var/www/html/lacito/" local="128273482080000000" remote="128273482080000000" />
<file name="leblic_kanak65.jpg" server="newhttpd.vjf.cnrs.fr//var/www/html/lacito/" local="129140699970000000" remote="129140699970000000" />
<file name="paris_c-d-lacito250.jpg" server="newhttpd.vjf.cnrs.fr//var/www/html/lacito/" local="128273482230000000" remote="128273482230000000" />
<file name="paris_c-d-lacito65.jpg" server="newhttpd.vjf.cnrs.fr//var/www/html/lacito/" local="129140699970000000" remote="129140699970000000" />
<file name="taine_dicohassan8_250.jpg" server="newhttpd.vjf.cnrs.fr//var/www/html/lacito/" local="128273482350000000" remote="128273482350000000" />
<file name="taine_dicohassan8_65.jpg" server="newhttpd.vjf.cnrs.fr//var/www/html/lacito/" local="129140699970000000" remote="129140699970000000" />
<file name="taine_lexhassan250.jpg" server="newhttpd.vjf.cnrs.fr//var/www/html/lacito/" local="128273482420000000" remote="128273482420000000" />
<file name="taine_lexhassan65.jpg" server="newhttpd.vjf.cnrs.fr//var/www/html/lacito/" local="129140699950000000" remote="129140699950000000" />
<file name="coyaud_arbres250.jpg" server="newhttpd.vjf.cnrs.fr//var/www/html/lacito/" local="128275321660000000" remote="128275321660000000" />
<file name="coyaud_arbres65.jpg" server="newhttpd.vjf.cnrs.fr//var/www/html/lacito/" local="129140699960000000" remote="129140699960000000" />
<file name="Motte_petitesbetes250.jpg" server="newhttpd.vjf.cnrs.fr//var/www/html/lacito/" local="128296790470000000" remote="128296790470000000" />
<file name="Motte_petitesbetes65.jpg" server="newhttpd.vjf.cnrs.fr//var/www/html/lacito/" local="129140699960000000" remote="129140699960000000" />
<file name="elephant_mouche300.jpg" server="newhttpd.vjf.cnrs.fr//var/www/html/lacito/" local="128296790600000000" remote="128296790600000000" />
<file name="grenouilles300.jpg" server="newhttpd.vjf.cnrs.fr//var/www/html/lacito/" local="128296790630000000" remote="128296790630000000" />
<file name="FdL29_250.jpg" server="newhttpd.vjf.cnrs.fr//var/www/html/lacito/" local="128330214270000000" remote="128330214270000000" />
<file name="FdL29_65.jpg" server="newhttpd.vjf.cnrs.fr//var/www/html/lacito/" local="129140699870000000" remote="129140699870000000" />
<file name="coyaud_coraux250.jpg" server="newhttpd.vjf.cnrs.fr//var/www/html/lacito/" local="128331442650000000" remote="128331442650000000" />
<file name="clo59-60_250.jpg" server="newhttpd.vjf.cnrs.fr//var/www/html/lacito/" local="128371915570000000" remote="128371915570000000" />
<file name="clo59-60_65.jpg" server="newhttpd.vjf.cnrs.fr//var/www/html/lacito/" local="129140699860000000" remote="129140699860000000" />
<file name="symbolisme250.jpg" server="newhttpd.vjf.cnrs.fr//var/www/html/lacito/" local="128435199300000000" remote="128435199300000000" />
<file name="symbolisme65.jpg" server="newhttpd.vjf.cnrs.fr//var/www/html/lacito/" local="129140699850000000" remote="129140699850000000" />
<file name="oisillon250.jpg" server="newhttpd.vjf.cnrs.fr//var/www/html/lacito/" local="128438401610000000" remote="128438401610000000" />
<file name="oisillon65.jpg" server="newhttpd.vjf.cnrs.fr//var/www/html/lacito/" local="128438401640000000" remote="128438401640000000" />
<file name="racine-issa_kikae250.jpg" server="newhttpd.vjf.cnrs.fr//var/www/html/lacito/" local="128484206790000000" remote="128484206790000000" />
<file name="racine-issa_kikae65.jpg" server="newhttpd.vjf.cnrs.fr//var/www/html/lacito/" local="128484206830000000" remote="128484206830000000" />
<file name="Coyaud-oeillets250.jpg" server="newhttpd.vjf.cnrs.fr//var/www/html/lacito/" local="128515273150000000" remote="128515273150000000" />
<file name="Coyaud-oeillets65.jpg" server="newhttpd.vjf.cnrs.fr//var/www/html/lacito/" local="128515273190000000" remote="128515273190000000" />
<file name="Adamou_grece250.jpg" server="newhttpd.vjf.cnrs.fr//var/www/html/lacito/" local="128515400700000000" remote="128515400700000000" />
<file name="Adamou_grece65.jpg" server="newhttpd.vjf.cnrs.fr//var/www/html/lacito/" local="128515400730000000" remote="128515400730000000" />
<file name="fontaine_paroles250.jpg" server="newhttpd.vjf.cnrs.fr//var/www/html/lacito/" local="128593832200000000" remote="128593832200000000" />
<file name="fontaine_paroles65.jpg" server="newhttpd.vjf.cnrs.fr//var/www/html/lacito/" local="128593832240000000" remote="128593832240000000" />
<file name="fontaine_recits250.jpg" server="newhttpd.vjf.cnrs.fr//var/www/html/lacito/" local="128593845740000000" remote="128593845740000000" />
<file name="fontaine_recits65.jpg" server="newhttpd.vjf.cnrs.fr//var/www/html/lacito/" local="128593845780000000" remote="128593845780000000" />
<file name="personnes250.jpg" server="newhttpd.vjf.cnrs.fr//var/www/html/lacito/" local="128596609520000000" remote="128596609520000000" />
<file name="personnes65.jpg" server="newhttpd.vjf.cnrs.fr//var/www/html/lacito/" local="128596609550000000" remote="128596609550000000" />
<file name="Kokborok250.jpg" server="newhttpd.vjf.cnrs.fr//var/www/html/lacito/" local="128623277590000000" remote="128623277590000000" />
<file name="Kokborok65.jpg" server="newhttpd.vjf.cnrs.fr//var/www/html/lacito/" local="128623277590000000" remote="128623277590000000" />
<file name="lidil37_250.jpg" server="newhttpd.vjf.cnrs.fr//var/www/html/lacito/" local="128665591320000000" remote="128665591320000000" />
<file name="lidil37_65.jpg" server="newhttpd.vjf.cnrs.fr//var/www/html/lacito/" local="128665591320000000" remote="128665591320000000" />
<file name="Jacquesson_anticode250.jpg" server="newhttpd.vjf.cnrs.fr//var/www/html/lacito/" local="3305275891" remote="1368434497149895252" />
<file name="mer-terre-kanak250.jpg" server="newhttpd.vjf.cnrs.fr//var/www/html/lacito/" local="128674144340000000" remote="128674144340000000" />
<file name="mer-terre-kanak65.jpg" server="newhttpd.vjf.cnrs.fr//var/www/html/lacito/" local="128674144340000000" remote="128674144340000000" />
<file name="taine_zenaga250.jpg" server="newhttpd.vjf.cnrs.fr//var/www/html/lacito/" local="128744070350000000" remote="128744070350000000" />
<file name="taine_zenaga65.jpg" server="newhttpd.vjf.cnrs.fr//var/www/html/lacito/" local="128735722240000000" remote="128735722240000000" />
<file name="randa_ours250.jpg" server="newhttpd.vjf.cnrs.fr//var/www/html/lacito/" local="128762456270000000" remote="128762456270000000" />
<file name="randa_ours65.jpg" server="newhttpd.vjf.cnrs.fr//var/www/html/lacito/" local="128762456270000000" remote="128762456270000000" />
<file name="anakesaAfrique250.jpg" server="newhttpd.vjf.cnrs.fr//var/www/html/lacito/" local="128762500010000000" remote="128762500010000000" />
<file name="anakesaAfrique65.jpg" server="newhttpd.vjf.cnrs.fr//var/www/html/lacito/" local="128762500010000000" remote="128762500010000000" />
<file name="BusikondeSama250.jpg" server="newhttpd.vjf.cnrs.fr//var/www/html/lacito/" local="128762500070000000" remote="128762500070000000" />
<file name="BusikondeSama65.jpg" server="newhttpd.vjf.cnrs.fr//var/www/html/lacito/" local="128762500070000000" remote="128762500070000000" />
<file name="jacquesson_anticode250.jpg" server="newhttpd.vjf.cnrs.fr//var/www/html/lacito/" local="128763145940000000" remote="128763145940000000" />
<file name="jacquesson_anticode65.jpg" server="newhttpd.vjf.cnrs.fr//var/www/html/lacito/" local="128763178540000000" remote="128763178540000000" />
<file name="anakesaChaynes250.jpg" server="newhttpd.vjf.cnrs.fr//var/www/html/lacito/" local="128763195800000000" remote="128763195800000000" />
<file name="anakesaChaynes65.jpg" server="newhttpd.vjf.cnrs.fr//var/www/html/lacito/" local="128763195810000000" remote="128763195810000000" />
<file name="jso126-127_250.jpg" server="newhttpd.vjf.cnrs.fr//var/www/html/lacito/" local="128768559430000000" remote="128768559430000000" />
<file name="jso126-127_65.jpg" server="newhttpd.vjf.cnrs.fr//var/www/html/lacito/" local="128768559430000000" remote="128768559430000000" />
<file name="JSO122-123_250.jpg" server="newhttpd.vjf.cnrs.fr//var/www/html/lacito/" local="128781355700000000" remote="128781355700000000" />
<file name="JSO122-123_65.jpg" server="newhttpd.vjf.cnrs.fr//var/www/html/lacito/" local="128781355700000000" remote="128781355700000000" />
<file name="transitions250.jpg" server="newhttpd.vjf.cnrs.fr//var/www/html/lacito/" local="128817842380000000" remote="128817842380000000" />
<file name="transitions65.jpg" server="newhttpd.vjf.cnrs.fr//var/www/html/lacito/" local="128817842380000000" remote="128817842380000000" />
<file name="coyaud_japon250.jpg" server="newhttpd.vjf.cnrs.fr//var/www/html/lacito/" local="128820424480000000" remote="128820424480000000" />
<file name="coyaud_japon65.jpg" server="newhttpd.vjf.cnrs.fr//var/www/html/lacito/" local="128820424480000000" remote="128820424480000000" />
<file name="etapes250.jpg" server="newhttpd.vjf.cnrs.fr//var/www/html/lacito/" local="128829829900000000" remote="128829829900000000" />
<file name="etapes65.jpg" server="newhttpd.vjf.cnrs.fr//var/www/html/lacito/" local="128829829900000000" remote="128829829900000000" />
<file name="A&S33_250.jpg" server="newhttpd.vjf.cnrs.fr//var/www/html/lacito/" local="128885811130000000" remote="128885811130000000" />
<file name="A&S33_85.jpg" server="newhttpd.vjf.cnrs.fr//var/www/html/lacito/" local="128885811130000000" remote="128885811130000000" />
<file name="Coyaud_saisons250.jpg" server="newhttpd.vjf.cnrs.fr//var/www/html/lacito/" local="128891935840000000" remote="128891935840000000" />
<file name="Coyaud_saisons65.jpg" server="newhttpd.vjf.cnrs.fr//var/www/html/lacito/" local="128891935840000000" remote="128891935840000000" />
<file name="mahieu-tersis250.jpg" server="newhttpd.vjf.cnrs.fr//var/www/html/lacito/" local="128903302390000000" remote="128903302390000000" />
<file name="mahieu-tersis65.jpg" server="newhttpd.vjf.cnrs.fr//var/www/html/lacito/" local="128903302390000000" remote="128903302390000000" />
<file name="naim_arabe-de-sanaa250.jpg" server="newhttpd.vjf.cnrs.fr//var/www/html/lacito/" local="128999222160000000" remote="128999222160000000" />
<file name="naim_arabe-de-sanaa65.jpg" server="newhttpd.vjf.cnrs.fr//var/www/html/lacito/" local="128999222160000000" remote="128999222160000000" />
<file name="HommagesLemarechal250.jpg" server="newhttpd.vjf.cnrs.fr//var/www/html/lacito/" local="129000734380000000" remote="129000734380000000" />
<file name="HommagesLemarechal65.jpg" server="newhttpd.vjf.cnrs.fr//var/www/html/lacito/" local="129000734410000000" remote="129000734410000000" />
<file name="aka_II_9_250.jpg" server="newhttpd.vjf.cnrs.fr//var/www/html/lacito/" local="129031995570000000" remote="129031995570000000" />
<file name="aka_II_9_65.jpg" server="newhttpd.vjf.cnrs.fr//var/www/html/lacito/" local="129031995570000000" remote="129031995570000000" />
<file name="aka_II_6_250.jpg" server="newhttpd.vjf.cnrs.fr//var/www/html/lacito/" local="129035351180000000" remote="129035351180000000" />
<file name="aka_I_1_250.jpg" server="newhttpd.vjf.cnrs.fr//var/www/html/lacito/" local="129035447230000000" remote="129035447230000000" />
<file name="aka_I_1_65.jpg" server="newhttpd.vjf.cnrs.fr//var/www/html/lacito/" local="129035447230000000" remote="129035447230000000" />
<file name="aka_I_2_250.jpg" server="newhttpd.vjf.cnrs.fr//var/www/html/lacito/" local="129035447230000000" remote="129035447230000000" />
<file name="aka_I_2_65.jpg" server="newhttpd.vjf.cnrs.fr//var/www/html/lacito/" local="129035447230000000" remote="129035447230000000" />
<file name="aka_I_3_250.jpg" server="newhttpd.vjf.cnrs.fr//var/www/html/lacito/" local="129035447230000000" remote="129035447230000000" />
<file name="aka_I_3_65.jpg" server="newhttpd.vjf.cnrs.fr//var/www/html/lacito/" local="129035447230000000" remote="129035447230000000" />
<file name="aka_I_4_250.jpg" server="newhttpd.vjf.cnrs.fr//var/www/html/lacito/" local="129035447230000000" remote="129035447230000000" />
<file name="aka_I_4_65.jpg" server="newhttpd.vjf.cnrs.fr//var/www/html/lacito/" local="129035447230000000" remote="129035447230000000" />
<file name="aka_II_2_250.jpg" server="newhttpd.vjf.cnrs.fr//var/www/html/lacito/" local="129035447450000000" remote="129035447450000000" />
<file name="aka_II_2_65.jpg" server="newhttpd.vjf.cnrs.fr//var/www/html/lacito/" local="129035447450000000" remote="129035447450000000" />
<file name="aka_II_3_250.jpg" server="newhttpd.vjf.cnrs.fr//var/www/html/lacito/" local="129035447450000000" remote="129035447450000000" />
<file name="aka_II_3_65.jpg" server="newhttpd.vjf.cnrs.fr//var/www/html/lacito/" local="129035447450000000" remote="129035447450000000" />
<file name="aka_II_4_250.jpg" server="newhttpd.vjf.cnrs.fr//var/www/html/lacito/" local="129035447450000000" remote="129035447450000000" />
<file name="aka_II_4_65.jpg" server="newhttpd.vjf.cnrs.fr//var/www/html/lacito/" local="129035447450000000" remote="129035447450000000" />
<file name="Lemarechal_typologie250.jpg" server="newhttpd.vjf.cnrs.fr//var/www/html/lacito/" local="129328311690000000" remote="129328311690000000" />
<file name="Lemarechal_typologie65.jpg" server="newhttpd.vjf.cnrs.fr//var/www/html/lacito/" local="129053432660000000" remote="129053432660000000" />
<file name="melakarta250.jpg" server="newhttpd.vjf.cnrs.fr//var/www/html/lacito/" local="129126167190000000" remote="129126167190000000" />
<file name="melakarta65.jpg" server="newhttpd.vjf.cnrs.fr//var/www/html/lacito/" local="129126167190000000" remote="129126167190000000" />
<file name="Ozanne_nyelayu65.jpg" server="newhttpd.vjf.cnrs.fr//var/www/html/lacito/" local="129140699970000000" remote="129140699970000000" />
<file name="Ozanne_nyelayu250.jpg" server="newhttpd.vjf.cnrs.fr//var/www/html/lacito/" local="129140700200000000" remote="129140700200000000" />
<file name="sherpa250.jpg" server="newhttpd.vjf.cnrs.fr//var/www/html/lacito/" local="129155490990000000" remote="129155490990000000" />
<file name="sherpa65.jpg" server="newhttpd.vjf.cnrs.fr//var/www/html/lacito/" local="129155490990000000" remote="129155490990000000" />
<file name="sherpa65.jpg" server="Macintosh HD/Applications/MAMP/htdocs/siteweb-lacito" local="3353910429" remote="1487836220114902173" />
<file name="melakarta65.jpg" server="Macintosh HD/Applications/MAMP/htdocs/siteweb-lacito" local="3350994729" remote="1487836220111986473" />
<file name="Lemarechal_typologie65.jpg" server="Macintosh HD/Applications/MAMP/htdocs/siteweb-lacito" local="3343737704" remote="1487836220104729448" />
<file name="hommages_137.jpg" server="Macintosh HD/Applications/MAMP/htdocs/siteweb-lacito" local="3263803649" remote="1487836220024795393" />
<file name="bujeaud250.jpg" server="newhttpd.vjf.cnrs.fr//var/www/html/lacito/" local="129177177370000000" remote="129177177370000000" />
<file name="bujeaud65.jpg" server="newhttpd.vjf.cnrs.fr//var/www/html/lacito/" local="129177177400000000" remote="129177177400000000" />
<file name="bujeaud65.jpg" server="Macintosh HD/Applications/MAMP/htdocs/siteweb-lacito" local="3356088920" remote="1479314111648619096" />
<file name="guerin_syntaxe250.jpg" server="newhttpd.vjf.cnrs.fr//var/www/html/lacito/" local="129228214720000000" remote="129228214720000000" />
<file name="guerin_syntaxe65.jpg" server="newhttpd.vjf.cnrs.fr//var/www/html/lacito/" local="129228214720000000" remote="129228214720000000" />
<file name="taine_fr-zenaga250.jpg" server="newhttpd.vjf.cnrs.fr//var/www/html/lacito/" local="129240048230000000" remote="129240048230000000" />
<file name="taine_fr-zenaga65.jpg" server="newhttpd.vjf.cnrs.fr//var/www/html/lacito/" local="129240048230000000" remote="129240048230000000" />
<file name="taine_fr-zenaga65.jpg" server="C:/Program Files/EasyPHP-5.3.2/www/lacito2/" local="129240084230000000" remote="129240084230000000" />
<file name="guerin_syntaxe65.jpg" server="C:/Program Files/EasyPHP-5.3.2/www/lacito2/" local="129228250720000000" remote="129228250720000000" />
<file name="melakarta65.jpg" server="C:/Program Files/EasyPHP-5.3.2/www/lacito2/" local="129126203190000000" remote="129126203190000000" />
<file name="bujeaud65.jpg" server="C:/Program Files/EasyPHP-5.3.2/www/lacito2/" local="129177213400000000" remote="129177213400000000" />
<file name="Lemarechal_typologie65.jpg" server="C:/Program Files/EasyPHP-5.3.2/www/lacito2/" local="129053468660000000" remote="129053468660000000" />
<file name="hommages_137.jpg" server="C:/Program Files/EasyPHP-5.3.2/www/lacito2/" local="129364482610000000" remote="129364482610000000" />
<file name="mukherjee_independance250.jpg" server="newhttpd.vjf.cnrs.fr//var/www/html/lacito/" local="129319608550000000" remote="129319608550000000" />
<file name="coyaud_poesie-chinoise65.jpg" server="newhttpd.vjf.cnrs.fr//var/www/html/lacito/" local="129386994250000000" remote="129386994250000000" />
<file name="enquete-description1_65.jpg" server="newhttpd.vjf.cnrs.fr//var/www/html/lacito/" local="129387142140000000" remote="129387142140000000" />
<file name="enquete-description2_65.jpg" server="newhttpd.vjf.cnrs.fr//var/www/html/lacito/" local="129387142140000000" remote="129387142140000000" />
<file name="naim_al-yaman65.jpg" server="newhttpd.vjf.cnrs.fr//var/www/html/lacito/" local="129387881610000000" remote="129387881610000000" />
<file name="coyaud_saisons250.jpg" server="newhttpd.vjf.cnrs.fr//var/www/html/lacito/" local="129386994310000000" remote="129386994310000000" />
<file name="bril_clauselinking65.jpg" server="newhttpd.vjf.cnrs.fr//var/www/html/lacito/" local="129352581530000000" remote="129352581530000000" />
<file name="coyaud_poesie-chinoise250.jpg" server="newhttpd.vjf.cnrs.fr//var/www/html/lacito/" local="129386994250000000" remote="129386994250000000" />
<file name="coyaud_samsara65.jpg" server="newhttpd.vjf.cnrs.fr//var/www/html/lacito/" local="129387020160000000" remote="129387020160000000" />
<file name="naim_yemen250.jpg" server="newhttpd.vjf.cnrs.fr//var/www/html/lacito/" local="129387868900000000" remote="129387868900000000" />
<file name="thomas_contes-ngbaka-mabo65.jpg" server="newhttpd.vjf.cnrs.fr//var/www/html/lacito/" local="129387115780000000" remote="129387115780000000" />
<file name="enquete-description3_65.jpg" server="newhttpd.vjf.cnrs.fr//var/www/html/lacito/" local="129387142140000000" remote="129387142140000000" />
<file name="coyaud_saisons65.jpg" server="newhttpd.vjf.cnrs.fr//var/www/html/lacito/" local="129386994310000000" remote="129386994310000000" />
<file name="coyaud_samsara250.jpg" server="newhttpd.vjf.cnrs.fr//var/www/html/lacito/" local="129387020160000000" remote="129387020160000000" />
<file name="naim_beyrouth65.jpg" server="newhttpd.vjf.cnrs.fr//var/www/html/lacito/" local="129387868890000000" remote="129387868890000000" />
<file name="naim_al-yaman250.jpg" server="newhttpd.vjf.cnrs.fr//var/www/html/lacito/" local="129387881610000000" remote="129387881610000000" />
<file name="enquete-description3_250.jpg" server="newhttpd.vjf.cnrs.fr//var/www/html/lacito/" local="129387142140000000" remote="129387142140000000" />
<file name="naim_beyrouth250.jpg" server="newhttpd.vjf.cnrs.fr//var/www/html/lacito/" local="129387868890000000" remote="129387868890000000" />
<file name="bril_clauselinking250.jpg" server="newhttpd.vjf.cnrs.fr//var/www/html/lacito/" local="129352581530000000" remote="129352581530000000" />
<file name="enquete-description1_250.jpg" server="newhttpd.vjf.cnrs.fr//var/www/html/lacito/" local="129387142140000000" remote="129387142140000000" />
<file name="enquete-description2_250.jpg" server="newhttpd.vjf.cnrs.fr//var/www/html/lacito/" local="129387142140000000" remote="129387142140000000" />
<file name="thomas_contes-ngbaka-mabo250.jpg" server="newhttpd.vjf.cnrs.fr//var/www/html/lacito/" local="129387115780000000" remote="129387115780000000" />
<file name="naim_yemen65.jpg" server="newhttpd.vjf.cnrs.fr//var/www/html/lacito/" local="129387868900000000" remote="129387868900000000" />
<file name="mukherjee_independance65.jpg" server="newhttpd.vjf.cnrs.fr//var/www/html/lacito/" local="129319608550000000" remote="129319608550000000" />
<file name="bril_clauselinking65.jpg" server="C:/Program Files/EasyPHP-5.3.2/www/lacito2/" local="129352581530000000" remote="129352581530000000" />
<file name="HommagesLemarechal65.jpg" server="C:/Program Files/EasyPHP-5.3.2/www/lacito2/" local="129000734410000000" remote="129000734410000000" />
<file name="mukherjee_independance65.jpg" server="C:/Program Files/EasyPHP-5.3.2/www/lacito2/" local="129319608550000000" remote="129319608550000000" />
<file name="medisance250.jpg" server="newhttpd.vjf.cnrs.fr//var/www/html/lacito/" local="129401846890000000" remote="129401846890000000" />
<file name="Aka_II_8_250.jpg" server="newhttpd.vjf.cnrs.fr//var/www/html/lacito/" local="129488961300000000" remote="129488961300000000" />
<file name="aka_II_1_250.jpg" server="newhttpd.vjf.cnrs.fr//var/www/html/lacito/" local="129488955240000000" remote="129488955240000000" />
<file name="aka_II_5_250.jpg" server="newhttpd.vjf.cnrs.fr//var/www/html/lacito/" local="129488955330000000" remote="129488955330000000" />
<file name="aka_II_10_65.jpg" server="newhttpd.vjf.cnrs.fr//var/www/html/lacito/" local="129530464170000000" remote="129530464170000000" />
<file name="colombel_la-langue-ouldeme65.jpg" server="newhttpd.vjf.cnrs.fr//var/www/html/lacito/" local="129500244280000000" remote="129500244280000000" />
<file name="colombel_la-langue-ouldeme250.jpg" server="newhttpd.vjf.cnrs.fr//var/www/html/lacito/" local="129500244280000000" remote="129500244280000000" />
<file name="aka_II_10_250.jpg" server="newhttpd.vjf.cnrs.fr//var/www/html/lacito/" local="129530464170000000" remote="129530464170000000" />
<file name="aka_II_10_65.jpg" server="C:/Program Files/EasyPHP-5.3.2/www/lacito2/" local="129530464170000000" remote="129530464170000000" />
<file name="valma_lslt19_250.jpg" server="newhttpd.vjf.cnrs.fr//var/www/html/lacito/" local="129629763470000000" remote="129629763470000000" />
<file name="valma_lslt19_65.jpg" server="newhttpd.vjf.cnrs.fr//var/www/html/lacito/" local="129629763800000000" remote="129629763800000000" />
<file name="moyse_topics65.jpg" server="newhttpd.vjf.cnrs.fr//var/www/html/lacito/" local="129645513560000000" remote="129645513560000000" />
<file name="leblic-maagenin200.jpg" server="newhttpd.vjf.cnrs.fr//var/www/html/lacito/" local="129616904740000000" remote="129616904740000000" />
<file name="Valma_LSLT19_250.jpg" server="newhttpd.vjf.cnrs.fr//var/www/html/lacito/" local="129629762960000000" remote="129629762960000000" />
<file name="moyse_topics250.jpg" server="newhttpd.vjf.cnrs.fr//var/www/html/lacito/" local="129645513560000000" remote="129645513560000000" />
<file name="Valma_LSLT19_65.jpg" server="newhttpd.vjf.cnrs.fr//var/www/html/lacito/" local="129629762960000000" remote="129629762960000000" />
<file name="leblic-maagenin-600.jpg" server="newhttpd.vjf.cnrs.fr//var/www/html/lacito/" local="129616907730000000" remote="129616907730000000" />
<file name="Lemarechal_typologie250.jpg" server="C:/Program Files/EasyPHP-5.3.2/www/lacito2/" local="129328347690000000" remote="129328347690000000" />
<file name="L&S139_65.jpg" server="newhttpd.vjf.cnrs.fr//var/www/html/lacito/" local="129750774380000000" remote="129750774380000000" />
<file name="lebarbier_contes250.jpg" server="newhttpd.vjf.cnrs.fr//var/www/html/lacito/" local="129730147640000000" remote="129730147640000000" />
<file name="Henri_Sungwadia250.jpg" server="newhttpd.vjf.cnrs.fr//var/www/html/lacito/" local="129678164610000000" remote="129678164610000000" />
<file name="stuf_65-1_250.jpg" server="newhttpd.vjf.cnrs.fr//var/www/html/lacito/" local="129797542800000000" remote="129797542800000000" />
<file name="langage&societe_sp.jpg" server="newhttpd.vjf.cnrs.fr//var/www/html/lacito/" local="129739451030000000" remote="129739451030000000" />
<file name="L&S139_250.jpg" server="newhttpd.vjf.cnrs.fr//var/www/html/lacito/" local="129750774380000000" remote="129750774380000000" />
<file name="fernandez-sami65.jpg" server="newhttpd.vjf.cnrs.fr//var/www/html/lacito/" local="129791421220000000" remote="129791421220000000" />
<file name="stuf_65-1_65.jpg" server="newhttpd.vjf.cnrs.fr//var/www/html/lacito/" local="129797542310000000" remote="129797542310000000" />
<file name="lebarbier_contes65.jpg" server="newhttpd.vjf.cnrs.fr//var/www/html/lacito/" local="129730147640000000" remote="129730147640000000" />
<file name="Henri_Sungwadia65.jpg" server="newhttpd.vjf.cnrs.fr//var/www/html/lacito/" local="129678164610000000" remote="129678164610000000" />
<file name="fernandez-sami250.jpg" server="newhttpd.vjf.cnrs.fr//var/www/html/lacito/" local="129791421220000000" remote="129791421220000000" />
<file name="stuf_65-1_65.jpg" server="C:/Program Files/EasyPHP-5.3.2/www/lacito2/" local="129797542310000000" remote="129797542310000000" />
<file name="lebarbier_contes65.jpg" server="C:/Program Files/EasyPHP-5.3.2/www/lacito2/" local="129730147640000000" remote="129730147640000000" />
<file name="fernandez-sami65.jpg" server="C:/Program Files/EasyPHP-5.3.2/www/lacito2/" local="129791421220000000" remote="129791421220000000" />
<file name="L&S139_65.jpg" server="C:/Program Files/EasyPHP-5.3.2/www/lacito2/" local="129750774380000000" remote="129750774380000000" />
<file name="Henri_Sungwadia65.jpg" server="C:/Program Files/EasyPHP-5.3.2/www/lacito2/" local="129678164610000000" remote="129678164610000000" />
<file name="moyse_topics65.jpg" server="C:/Program Files/EasyPHP-5.3.2/www/lacito2/" local="129645513560000000" remote="129645513560000000" />
</dwsync>